LICENSE
MANIFEST.in
README.md
setup.py
drfapikey.egg-info/PKG-INFO
drfapikey.egg-info/SOURCES.txt
drfapikey.egg-info/dependency_links.txt
drfapikey.egg-info/top_level.txt
rest_framework_api_key/__init__.py
rest_framework_api_key/admin.py
rest_framework_api_key/helpers.py
rest_framework_api_key/models.py
rest_framework_api_key/permissions.py
tests/__init__.py
tests/settings.py
tests/test_admin.py
tests/test_models.py
tests/test_views.py
tests/urls.py
tests/views.py